{"items": [
                {
                        "name": "Factory Metrics",
                        "place": "FactoryMetricsPlace:",
                        "items": [
                                {
                                        "name": "Houston CCM5",
                                        "place": "NoWhere:",
                                        "items": [
                                                {
                                                        "name": "Overall Metrics",
                                                        "place" : "LatestTaskExecutionPlace:619287"
                                                 },
                                                {
                                                        "name": "Product Groups",
                                                        "place" : "LatestTaskExecutionPlace:828653"
                                                },
                                                {
                                                        "name": "Key Products",
                                                        "place" : "LatestTaskExecutionPlace:6320759"
                                                }
                                        ]
                                },
                                {
                                        "name": "Singapore",
                                        "place": "NoWhere:",
                                        "items": [
                                                {
                                                        "name": "Overall Metrics",
                                                        "place" : "LatestTaskExecutionPlace:8306887"
                                                },
                                                {
                                                        "name": "Product Groups",
                                                        "place" : "LatestTaskExecutionPlace:8306908"
                                                },
                                                {
                                                        "name": "Key Products",
                                                        "place" : "LatestTaskExecutionPlace:8812073"
                                                }
                                        ]
 
                                 }
                       ]
                },
                {
                        "name" : "Supplier Metrics",
                        "place": "NoWhere:",
                        "items": [
                                {
                                        "name": "Memory",
                                        "place" : "LatestTaskExecutionPlace:10088688"
                                 }
                        ]
                }
        ]
}
